<?xml version="1.0" encoding="utf-8"?>
<clothing-items>
 <clothing>
  <id>
   202228737
  </id>
  <name>
   Ellesse Skirt T-7412
  </name>
  <category>
   Skirt
  </category>
  <size>
   XL
  </size>
  <color>
   Синий
  </color>
  <material>
   Полиэстер
  </material>
  <price>
   692948
  </price>
  <rating>
   1.25
  </rating>
  <reviews>
   144903
  </reviews>
  <exclusive>
   no
  </exclusive>
 </clothing>
 <clothing>
  <id>
   688823505
  </id>
  <name>
   Fila Skirt R-2833
  </name>
  <category>
   Skirt
  </category>
  <size>
   M
  </size>
  <color>
   Оранжевый
  </color>
  <material>
   Шелк
  </material>
  <price>
   103303
  </price>
  <rating>
   2.43
  </rating>
  <reviews>
   701777
  </reviews>
  <exclusive>
   no
  </exclusive>
  <sporty>
   no
  </sporty>
 </clothing>
 <clothing>
  <id>
   830058837
  </id>
  <name>
   Brooks Jacket A-1640
  </name>
  <category>
   Jacket
  </category>
  <size>
   L
  </size>
  <color>
   Зеленый
  </color>
  <material>
   Вискоза
  </material>
  <price>
   679843
  </price>
  <rating>
   4.72
  </rating>
  <reviews>
   94983
  </reviews>
  <exclusive>
   yes
  </exclusive>
  <sporty>
   yes
  </sporty>
 </clothing>
 <clothing>
  <id>
   855731197
  </id>
  <name>
   Vans Skirt W-5963
  </name>
  <category>
   Skirt
  </category>
  <size>
   XXL
  </size>
  <color>
   Оранжевый
  </color>
  <material>
   Полиэстер
  </material>
  <price>
   392198
  </price>
  <rating>
   1.63
  </rating>
  <reviews>
   728259
  </reviews>
  <new>
   +
  </new>
  <exclusive>
   yes
  </exclusive>
  <sporty>
   no
  </sporty>
 </clothing>
 <clothing>
  <id>
   140381175
  </id>
  <name>
   PleinSport Hat Q-5244
  </name>
  <category>
   Hat
  </category>
  <size>
   L
  </size>
  <color>
   Зеленый
  </color>
  <material>
   Вискоза
  </material>
  <price>
   694365
  </price>
  <rating>
   4.13
  </rating>
  <reviews>
   54086
  </reviews>
  <exclusive>
   yes
  </exclusive>
 </clothing>
 <clothing>
  <id>
   210499861
  </id>
  <name>
   Brooks Jeans X-4945
  </name>
  <category>
   Jeans
  </category>
  <size>
   XL
  </size>
  <color>
   Зеленый
  </color>
  <material>
   Кожа
  </material>
  <price>
   356002
  </price>
  <rating>
   4.99
  </rating>
  <reviews>
   876564
  </reviews>
  <new>
   -
  </new>
  <sporty>
   no
  </sporty>
 </clothing>
 <clothing>
  <id>
   361450301
  </id>
  <name>
   New Balance Dress E-6801
  </name>
  <category>
   Dress
  </category>
  <size>
   S
  </size>
  <color>
   Желтый
  </color>
  <material>
   Хлопок
  </material>
  <price>
   466045
  </price>
  <rating>
   2.22
  </rating>
  <reviews>
   283087
  </reviews>
 </clothing>
 <clothing>
  <id>
   825223735
  </id>
  <name>
   Adidas Socks V-3294
  </name>
  <category>
   Socks
  </category>
  <size>
   M
  </size>
  <color>
   Желтый
  </color>
  <material>
   Кожа
  </material>
  <price>
   144934
  </price>
  <rating>
   4.32
  </rating>
  <reviews>
   438637
  </reviews>
  <new>
   -
  </new>
  <sporty>
   no
  </sporty>
 </clothing>
 <clothing>
  <id>
   737194243
  </id>
  <name>
   Addidas Skirt J-2430
  </name>
  <category>
   Skirt
  </category>
  <size>
   M
  </size>
  <color>
   Желтый
  </color>
  <material>
   Кожа
  </material>
  <price>
   190174
  </price>
  <rating>
   4.38
  </rating>
  <reviews>
   121682
  </reviews>
  <new>
   -
  </new>
  <exclusive>
   yes
  </exclusive>
 </clothing>
 <clothing>
  <id>
   959030083
  </id>
  <name>
   Asics Blouse S-4419
  </name>
  <category>
   Blouse
  </category>
  <size>
   XXL
  </size>
  <color>
   Оранжевый
  </color>
  <material>
   Хлопок
  </material>
  <price>
   248185
  </price>
  <rating>
   2.11
  </rating>
  <reviews>
   529418
  </reviews>
  <new>
   +
  </new>
  <exclusive>
   no
  </exclusive>
  <sporty>
   yes
  </sporty>
 </clothing>
 <clothing>
  <id>
   523717264
  </id>
  <name>
   DC Dress A-4800
  </name>
  <category>
   Dress
  </category>
  <size>
   L
  </size>
  <color>
   Синий
  </color>
  <material>
   Шелк
  </material>
  <price>
   910195
  </price>
  <rating>
   4.15
  </rating>
  <reviews>
   61157
  </reviews>
  <new>
   +
  </new>
  <exclusive>
   yes
  </exclusive>
  <sporty>
   no
  </sporty>
 </clothing>
 <clothing>
  <id>
   433613000
  </id>
  <name>
   Converse Gloves W-9500
  </name>
  <category>
   Gloves
  </category>
  <size>
   L
  </size>
  <color>
   Красный
  </color>
  <material>
   Полиэстер
  </material>
  <price>
   576252
  </price>
  <rating>
   1.51
  </rating>
  <reviews>
   22139
  </reviews>
  <exclusive>
   yes
  </exclusive>
  <sporty>
   no
  </sporty>
 </clothing>
 <clothing>
  <id>
   280077033
  </id>
  <name>
   New Balance Dress J-9243
  </name>
  <category>
   Dress
  </category>
  <size>
   S
  </size>
  <color>
   Голубой
  </color>
  <material>
   Нейлон
  </material>
  <price>
   652165
  </price>
  <rating>
   2.39
  </rating>
  <reviews>
   954914
  </reviews>
  <new>
   -
  </new>
 </clothing>
 <clothing>
  <id>
   267103994
  </id>
  <name>
   Converse Belts M-9569
  </name>
  <category>
   Belts
  </category>
  <size>
   L
  </size>
  <color>
   Желтый
  </color>
  <material>
   Шерсть
  </material>
  <price>
   697538
  </price>
  <rating>
   3.62
  </rating>
  <reviews>
   83787
  </reviews>
  <new>
   +
  </new>
  <exclusive>
   yes
  </exclusive>
  <sporty>
   yes
  </sporty>
 </clothing>
 <clothing>
  <id>
   528228930
  </id>
  <name>
   PleinSport Sweater K-5675
  </name>
  <category>
   Sweater
  </category>
  <size>
   L
  </size>
  <color>
   Желтый
  </color>
  <material>
   Лен
  </material>
  <price>
   585736
  </price>
  <rating>
   2.62
  </rating>
  <reviews>
   897309
  </reviews>
 </clothing>
 <clothing>
  <id>
   743566792
  </id>
  <name>
   Addidas T-shirt C-1671
  </name>
  <category>
   T-shirt
  </category>
  <size>
   XXL
  </size>
  <color>
   Оранжевый
  </color>
  <material>
   Кожа
  </material>
  <price>
   154097
  </price>
  <rating>
   2.51
  </rating>
  <reviews>
   847349
  </reviews>
  <new>
   -
  </new>
  <exclusive>
   no
  </exclusive>
 </clothing>
 <clothing>
  <id>
   993875103
  </id>
  <name>
   Nike Sweater W-6539
  </name>
  <category>
   Sweater
  </category>
  <size>
   S
  </size>
  <color>
   Оранжевый
  </color>
  <material>
   Шерсть
  </material>
  <price>
   373706
  </price>
  <rating>
   3.32
  </rating>
  <reviews>
   147959
  </reviews>
  <new>
   +
  </new>
  <exclusive>
   no
  </exclusive>
 </clothing>
 <clothing>
  <id>
   674685124
  </id>
  <name>
   New Balance Pants X-3208
  </name>
  <category>
   Pants
  </category>
  <size>
   S
  </size>
  <color>
   Голубой
  </color>
  <material>
   Полиэстер
  </material>
  <price>
   232511
  </price>
  <rating>
   3.79
  </rating>
  <reviews>
   337451
  </reviews>
  <new>
   +
  </new>
  <sporty>
   yes
  </sporty>
 </clothing>
 <clothing>
  <id>
   268799289
  </id>
  <name>
   Ellesse Blouse U-9058
  </name>
  <category>
   Blouse
  </category>
  <size>
   M
  </size>
  <color>
   Желтый
  </color>
  <material>
   Хлопок
  </material>
  <price>
   619038
  </price>
  <rating>
   2.78
  </rating>
  <reviews>
   650315
  </reviews>
  <new>
   -
  </new>
  <exclusive>
   yes
  </exclusive>
  <sporty>
   yes
  </sporty>
 </clothing>
</clothing-items>
